{
  "repo": "open-webui/open-webui",
  "url": "https://github.com/open-webui/open-webui.git",
  "status": "extracted",
  "copied_count": 7,
  "copied_files": [
    "docs/apache.md",
    "docs/CONTRIBUTING.md",
    "docs/README.md",
    "docs/SECURITY.md",
    "package.json",
    "pyproject.toml",
    "README.md"
  ],
  "notes": "Use templates/repo-extraction-report.md to complete semantic extraction.",
  "clone_log": "Cloning into 'C:\\Users\\karti\\Desktop\\foundation\\repo_intake\\_clones\\open-webui__open-webui'...\nUpdating files:   8% (437/4922)\nUpdating files:   9% (443/4922)\nUpdating files:  10% (493/4922)\nUpdating files:  11% (542/4922)\nUpdating files:  12% (591/4922)\nUpdating files:  13% (640/4922)\nUpdating files:  14% (690/4922)\nUpdating files:  15% (739/4922)\nUpdating files:  16% (788/4922)\nUpdating files:  17% (837/4922)\nUpdating files:  18% (886/4922)\nUpdating files:  19% (936/4922)\nUpdating files:  20% (985/4922)\nUpdating files:  21% (1034/4922)\nUpdating files:  22% (1083/4922)\nUpdating files:  23% (1133/4922)\nUpdating files:  24% (1182/4922)\nUpdating files:  25% (1231/4922)\nUpdating files:  26% (1280/4922)\nUpdating files:  27% (1329/4922)\nUpdating files:  28% (1379/4922)\nUpdating files:  29% (1428/4922)\nUpdating files:  30% (1477/4922)\nUpdating files:  31% (1526/4922)\nUpdating files:  32% (1576/4922)\nUpdating files:  32% (1615/4922)\nUpdating files:  33% (1625/4922)\nUpdating files:  34% (1674/4922)\nUpdating files:  35% (1723/4922)\nUpdating files:  36% (1772/4922)\nUpdating files:  37% (1822/4922)\nUpdating files:  38% (1871/4922)\nUpdating files:  39% (1920/4922)\nUpdating files:  40% (1969/4922)\nUpdating files:  41% (2019/4922)\nUpdating files:  42% (2068/4922)\nUpdating files:  43% (2117/4922)\nUpdating files:  44% (2166/4922)\nUpdating files:  45% (2215/4922)\nUpdating files:  46% (2265/4922)\nUpdating files:  47% (2314/4922)\nUpdating files:  48% (2363/4922)\nUpdating files:  49% (2412/4922)\nUpdating files:  50% (2461/4922)\nUpdating files:  51% (2511/4922)\nUpdating files:  52% (2560/4922)\nUpdating files:  53% (2609/4922)\nUpdating files:  54% (2658/4922)\nUpdating files:  55% (2708/4922)\nUpdating files:  56% (2757/4922)\nUpdating files:  57% (2806/4922)\nUpdating files:  58% (2855/4922)\nUpdating files:  59% (2904/4922)\nUpdating files:  60% (2954/4922)\nUpdating files:  61% (3003/4922)\nUpdating files:  62% (3052/4922)\nUpdating files:  62% (3063/4922)\nUpdating files:  63% (3101/4922)\nUpdating files:  64% (3151/4922)\nUpdating files:  65% (3200/4922)\nUpdating files:  66% (3249/4922)\nUpdating files:  67% (3298/4922)\nUpdating files:  68% (3347/4922)\nUpdating files:  69% (3397/4922)\nUpdating files:  70% (3446/4922)\nUpdating files:  71% (3495/4922)\nUpdating files:  72% (3544/4922)\nUpdating files:  73% (3594/4922)\nUpdating files:  74% (3643/4922)\nUpdating files:  75% (3692/4922)\nUpdating files:  76% (3741/4922)\nUpdating files:  77% (3790/4922)\nUpdating files:  78% (3840/4922)\nUpdating files:  79% (3889/4922)\nUpdating files:  80% (3938/4922)\nUpdating files:  81% (3987/4922)\nUpdating files:  82% (4037/4922)\nUpdating files:  83% (4086/4922)\nUpdating files:  84% (4135/4922)\nUpdating files:  85% (4184/4922)\nUpdating files:  86% (4233/4922)\nUpdating files:  87% (4283/4922)\nUpdating files:  88% (4332/4922)\nUpdating files:  89% (4381/4922)\nUpdating files:  90% (4430/4922)\nUpdating files:  90% (4471/4922)\nUpdating files:  91% (4480/4922)\nUpdating files:  92% (4529/4922)\nUpdating files:  93% (4578/4922)\nUpdating files:  94% (4627/4922)\nUpdating files:  95% (4676/4922)\nUpdating files:  96% (4726/4922)\nUpdating files:  97% (4775/4922)\nUpdating files:  98% (4824/4922)\nUpdating files:  99% (4873/4922)\nUpdating files: 100% (4922/4922)\nUpdating files: 100% (4922/4922), done."
}